LICENSE
MANIFEST.in
README.md
setup.py
djvsyepitb/__init__.py
djvsyepitb/api_helper.py
djvsyepitb/configuration.py
djvsyepitb/decorators.py
djvsyepitb/djvsyepitb_client.py
djvsyepitb.egg-info/PKG-INFO
djvsyepitb.egg-info/SOURCES.txt
djvsyepitb.egg-info/dependency_links.txt
djvsyepitb.egg-info/requires.txt
djvsyepitb.egg-info/top_level.txt
djvsyepitb/controllers/__init__.py
djvsyepitb/controllers/api_controller.py
djvsyepitb/controllers/base_controller.py
djvsyepitb/exceptions/__init__.py
djvsyepitb/exceptions/api_exception.py
djvsyepitb/http/__init__.py
djvsyepitb/http/http_call_back.py
djvsyepitb/http/http_client.py
djvsyepitb/http/http_context.py
djvsyepitb/http/http_method_enum.py
djvsyepitb/http/http_request.py
djvsyepitb/http/http_response.py
djvsyepitb/http/requests_client.py
djvsyepitb/http/auth/__init__.py
djvsyepitb/http/auth/basic_auth.py
djvsyepitb/models/__init__.py
djvsyepitb/models/suite_code_enum.py
tests/__init__.py
tests/http_response_catcher.py
tests/test_helper.py
tests/controllers/__init__.py
tests/controllers/controller_test_base.py
tests/controllers/test_api_controller.py